kolla_cli/__init__.py
kolla_cli/i18n.py
kolla_cli/shell.py
kolla_cli/api/__init__.py
kolla_cli/api/certificate.py
kolla_cli/api/client.py
kolla_cli/api/config.py
kolla_cli/api/control_plane.py
kolla_cli/api/exceptions.py
kolla_cli/api/group.py
kolla_cli/api/host.py
kolla_cli/api/job.py
kolla_cli/api/password.py
kolla_cli/api/properties.py
kolla_cli/api/service.py
kolla_cli/api/support.py
kolla_cli/commands/__init__.py
kolla_cli/commands/config.py
kolla_cli/commands/exceptions.py
kolla_cli/commands/group.py
kolla_cli/commands/host.py
kolla_cli/commands/kolla_action.py
kolla_cli/commands/mode.py
kolla_cli/commands/password.py
kolla_cli/commands/property.py
kolla_cli/commands/service.py
kolla_cli/commands/support.py
kolla_cli/common/__init__.py
kolla_cli/common/ansible_inventory.py
kolla_cli/common/host.py
kolla_cli/common/host_group.py
kolla_cli/common/inventory.py
kolla_cli/common/passwords.py
kolla_cli/common/properties.py
kolla_cli/common/service.py
kolla_cli/common/sshutils.py
kolla_cli/common/subservice.py
kolla_cli/common/support.py
kolla_cli/common/utils.py
kolla_cli/common/ansible/__init__.py
kolla_cli/common/ansible/actions.py
kolla_cli/common/ansible/job.py
kolla_cli/common/ansible/playbook.py
kolla_cli/common/ansible/utils.py
kolla_cli/tests/__init__.py
kolla_cli/tests/functional/README.txt
kolla_cli/tests/functional/__init__.py
kolla_cli/tests/functional/common.py
kolla_cli/tests/functional/functional_test_setup.sh
kolla_cli/tests/functional/inventory_test_file
kolla_cli/tests/functional/test_client_upgrade.py
kolla_cli/tests/functional/test_config.py
kolla_cli/tests/functional/test_deploy.py
kolla_cli/tests/functional/test_destroy.py
kolla_cli/tests/functional/test_group.py
kolla_cli/tests/functional/test_host.py
kolla_cli/tests/functional/test_password.py
kolla_cli/tests/functional/test_property.py
kolla_cli/tests/functional/test_reconfigure.py
kolla_cli/tests/functional/test_service.py
kolla_cli-10.0.0.dist-info/DESCRIPTION.rst
kolla_cli-10.0.0.dist-info/METADATA
kolla_cli-10.0.0.dist-info/RECORD
kolla_cli-10.0.0.dist-info/WHEEL
kolla_cli-10.0.0.dist-info/entry_points.txt
kolla_cli-10.0.0.dist-info/metadata.json
kolla_cli-10.0.0.dist-info/pbr.json
kolla_cli-10.0.0.dist-info/top_level.txt
