Metadata-Version: 2.0
Name: kolla-cli
Version: 10.0.0
Summary: Command Line Interface for Kolla-Ansible
Home-page: https://docs.openstack.org/kolla-cli/latest/
Author: OpenStack
Author-email: openstack-discuss@lists.openstack.org
License: Apache License, Version 2.0
Platform: UNKNOWN
Classifier: Environment :: OpenStack
Classifier: Intended Audience :: Developers
Classifier: Intended Audience :: Information Technology
Classifier: Intended Audience :: System Administrators
Classifier: License :: OSI Approved :: Apache Software License
Classifier: Operating System :: POSIX :: Linux
Classifier: Programming Language :: Python
Classifier: Programming Language :: Python :: Implementation :: CPython
Classifier: Programming Language :: Python :: 3 :: Only
Classifier: Programming Language :: Python :: 3
Classifier: Programming Language :: Python :: 3.6
Classifier: Programming Language :: Python :: 3.7
Requires-Python: >=3.6
Requires-Dist: cliff-tablib (>=2.0)
Requires-Dist: cliff (>=2.11.0)
Requires-Dist: docker (>=2.4.2)
Requires-Dist: docker (>=2.4.2)
Requires-Dist: jsonpickle (>=0.9)
Requires-Dist: oslo.i18n (>=3.20.0)
Requires-Dist: paramiko (>=2.6.0)
Requires-Dist: pbr (!=2.1.0,>=2.0.0)
